protosanity/__init__.py
protosanity/_version.py
protosanity/basic.py
protosanity/compile_pbs.py
protosanity/protoc.py
protosanity/protoc_gen_sanity.py
test/MANIFEST.in
test/Makefile
test/__init__.py
test/setup.py
test/test_compile_pbs.sh
test/test_health.sh
test/barlib/__init__.py
test/barlib/common_pb2.py
test/barlib/protobuf/__init__.py
test/barlib/protobuf/myservice_pb2.py
test/barlib/protobuf/myservice_pb2_grpc.py
test/foolib/__init__.py
test/foolib/client.py
test/foolib/compile_pb.py
test/foolib/server.py
test/foolib/util.py
test/foolib/protobuf/__init__.py
test/foolib/protobuf/common.proto
test/foolib/protobuf/common_pb2.py
test/foolib/protobuf/common_pb2_grpc.py
test/foolib/protobuf/myservice.proto
test/foolib/protobuf/myservice_pb2.py
test/foolib/protobuf/myservice_pb2_grpc.py
protosanity-0.0.5.dist-info/METADATA
protosanity-0.0.5.dist-info/WHEEL
protosanity-0.0.5.dist-info/entry_points.txt
protosanity-0.0.5.dist-info/top_level.txt
protosanity-0.0.5.dist-info/RECORD
